neofin_toobox/__init__.py
neofin_toobox/adapters/__init__.py
neofin_toobox/adapters/ses_adapter.py
neofin_toobox/adapters/sqs_adapter.py
neofin_toobox/configs/__init__.py
neofin_toobox/configs/enums.py
neofin_toobox/configs/otel_tracing/config.py
neofin_toobox/configs/otel_tracing/otel_middleware.py
neofin_toobox/configs/otel_tracing/span_events.py
neofin_toobox/exceptions/__init__.py
neofin_toobox/exceptions/adapters/__init__.py
neofin_toobox/exceptions/adapters/sqs_adapter_exception.py
neofin_toobox/exceptions/common_exceptions.py
neofin_toobox/exceptions/decorators/__init__.py
neofin_toobox/exceptions/decorators/auth_exceptions.py
neofin_toobox/exceptions/repositories/__init__.py
neofin_toobox/exceptions/repositories/company_repository_exception.py
neofin_toobox/exceptions/repositories/roles_repository_exception.py
neofin_toobox/exceptions/repositories/user_repository_exception.py
neofin_toobox/models/__init__.py
neofin_toobox/models/customers.py
neofin_toobox/models/renegotiation_campaign.py
neofin_toobox/repositories/__init__.py
neofin_toobox/repositories/audit_repository.py
neofin_toobox/repositories/billing_repository.py
neofin_toobox/repositories/company_repository.py
neofin_toobox/repositories/customer_repository.py
neofin_toobox/repositories/dynamodb_repository.py
neofin_toobox/repositories/installment_repository.py
neofin_toobox/repositories/renegotiation_campaign_repository.py
neofin_toobox/repositories/roles_repository.py
neofin_toobox/repositories/user_repository.py
neofin_toobox/test/test_example.py
neofin_toobox/test/test_otel_refactor.py
neofin_toobox/utils/__init__.py
neofin_toobox/utils/decorators/__init__.py
neofin_toobox/utils/decorators/audit.py
neofin_toobox/utils/decorators/auth_permission.py
neofin_toobox/utils/decorators/check_cors.py
neofin_toobox/utils/decorators/handler_error.py
neofin_toobox/utils/encoders.py
neofin_toobox/utils/helpers.py
neofin_toolbox-2.2.3.dist-info/METADATA
neofin_toolbox-2.2.3.dist-info/WHEEL
neofin_toolbox-2.2.3.dist-info/RECORD
