Metadata-Version: 2.4
Name: neofin-toolbox
Version: 2.2.3
Summary: Pacote utilitário do Neofin
Author: Neofin
Author-email: gitops@neofin.com.br
Requires-Python: >=3.10
Classifier: Programming Language :: Python :: 3
Classifier: Programming Language :: Python :: 3.10
Classifier: Programming Language :: Python :: 3.11
Classifier: Programming Language :: Python :: 3.12
Classifier: Programming Language :: Python :: 3.13
Classifier: Programming Language :: Python :: 3.14
Requires-Dist: boto3 (>=1.40.2,<2.0.0)
Requires-Dist: chalice (>=1.32.0,<2.0.0)
Requires-Dist: jinja2 (>=3.1.6,<4.0.0)
Requires-Dist: opentelemetry-api (>=1.24.0,<2.0.0)
Requires-Dist: opentelemetry-exporter-otlp-proto-grpc (>=1.24.0,<2.0.0)
Requires-Dist: opentelemetry-instrumentation-logging (>=0.44b0,<1.0.0)
Requires-Dist: opentelemetry-instrumentation-requests (>=0.44b0,<1.0.0)
Requires-Dist: opentelemetry-instrumentation-wsgi (>=0.44b0,<1.0.0)
Requires-Dist: opentelemetry-sdk (>=1.24.0,<2.0.0)
Requires-Dist: pydantic (>=2.11.7,<3.0.0)
Requires-Dist: python-decouple (>=3.8,<4.0)
